pq_solana_transfer_sdk/__init__.py
pq_solana_transfer_sdk/api.py
pq_solana_transfer_sdk-0.1.0.dist-info/METADATA
pq_solana_transfer_sdk-0.1.0.dist-info/WHEEL
pq_solana_transfer_sdk-0.1.0.dist-info/RECORD
