Metadata-Version: 2.1
Name: pq-solana-transfer-sdk
Version: 0.1.0
Summary: 
Author: wow-service
Author-email: gaoxu_cerber@126.com
Requires-Python: >=3.12,<4.0
Classifier: Programming Language :: Python :: 3
Classifier: Programming Language :: Python :: 3.12
Classifier: Programming Language :: Python :: 3.13
Requires-Dist: retrying (>=1.3.4,<2.0.0)
Requires-Dist: solana (==0.34.3)
